xtiler.py
xtiler-0.1.0.dist-info/METADATA
xtiler-0.1.0.dist-info/WHEEL
xtiler-0.1.0.dist-info/licenses/LICENSE
xtiler-0.1.0.dist-info/RECORD
