Metadata-Version: 2.3
Name: xtiler
Version: 0.1.0
Summary: Coordinate system for tiling with hexagons.
Project-URL: Documentation, https://github.com/LordPatate/hexa-tiling#readme
Project-URL: Issues, https://github.com/LordPatate/hexa-tiling/issues
Project-URL: Source, https://github.com/LordPatate/hexa-tiling
Author: Tom Bricaud
License-Expression: MIT
License-File: LICENSE
Keywords: coordinate,grid,hexagon,tiling
Classifier: Development Status :: 4 - Beta
Classifier: Programming Language :: Python
Classifier: Programming Language :: Python :: 3.8
Classifier: Programming Language :: Python :: 3.9
Classifier: Programming Language :: Python :: 3.10
Classifier: Programming Language :: Python :: 3.11
Classifier: Programming Language :: Python :: 3.12
Classifier: Programming Language :: Python :: Implementation :: CPython
Classifier: Programming Language :: Python :: Implementation :: PyPy
Requires-Python: >=3.8
